[
  {
    "columnName": "state",
    "width": 100,
    "wordWrappedEnabled": true
  },
  {
    "columnName": "product",
    "width": 100,
    "wordWrappedEnabled": true
  },
  {
    "columnName": "facepage",
    "width": 150,
    "wordWrappedEnabled": true
  },
  { 
    "columnName": "masterapp",
    "width": 200,
    "wordWrappedEnabled": true
  },
  {
    "columnName": "tableofcontents",
    "width": 200,
    "wordWrappedEnabled": true
  },
  {
    "columnName": "scheduleofbene",
    "width": 200,
    "wordWrappedEnabled": true
  },
  {
    "columnName": "definitions",
    "width": 150,
    "wordWrappedEnabled": true
  },
  {
    "columnName": "premiums",
    "width": 150,
    "wordWrappedEnabled": true
  },
  {
    "columnName": "certainresp",
    "width": 300,
    "wordWrappedEnabled": true
  },
  {
    "columnName": "genprovis",
    "width": 200,
    "wordWrappedEnabled": true
  },
  {
    "columnName": "indiveligdateterm",
    "width": 300,
    "wordWrappedEnabled": true
  },
  {
    "columnName": "depinsurance",
    "width": 200,
    "wordWrappedEnabled": true
  },
  {
    "columnName": "portability",
    "width": 150,
    "wordWrappedEnabled": true
  },
  {
    "columnName": "benprovis",
    "width": 200,
    "wordWrappedEnabled": true
  },
  {
    "columnName": "wellnessbenefit",
    "width": 200,
    "wordWrappedEnabled": true
  },
  {
    "columnName": "beneficiaryandfacilitypay",
    "width": 200,
    "wordWrappedEnabled": true
  },
  {
    "columnName": "claimsprovis",
    "width": 200,
    "wordWrappedEnabled": true
  },
  {
    "columnName": "extensionofcoveragefmla",
    "width": 200,
    "wordWrappedEnabled": true
  },
  {
    "columnName": "exclusions",
    "width": 150,
    "wordWrappedEnabled": true
  },
  {
    "columnName": "requirednotices",
    "width": 150,
    "wordWrappedEnabled": true
  },
  {
    "columnName": "additionalnotes",
    "width": 150,
    "wordWrappedEnabled": true
  },
  {
    "columnName": "certofcoverage",
    "width": 200,
    "wordWrappedEnabled": true
  },		
  {
    "columnName": "wheretofind",
    "width": 200,
    "wordWrappedEnabled": true
  },
  {
    "columnName": "introduction",
    "width": 150,
    "wordWrappedEnabled": true
  },
  {
    "columnName": "limitations",
    "width": 150,
    "wordWrappedEnabled": true
  },
  {
    "columnName": "limitationslateapp",
    "width": 230,
    "wordWrappedEnabled": true
  }, 	
  {
    "columnName": "policyholdersection",
    "width": 200,
    "wordWrappedEnabled": true
  },
  {
    "columnName": "typeofbenes",
    "width": 250,
    "wordWrappedEnabled": true
  },  	
  {
    "columnName": "xferofcoverage",
    "width": 200,
    "wordWrappedEnabled": true
  },
  {
    "columnName": "waivtotaldis",
    "width": 300,
    "wordWrappedEnabled": true
  },
  {
    "columnName": "waivconfine",
    "width": 300,
    "wordWrappedEnabled": true
  },
  {
    "columnName": "contofindins",
    "width": 200,
    "wordWrappedEnabled": true
  }
]